ragas_annotator/__init__.py
ragas_annotator/_modidx.py
ragas_annotator/core.py
ragas_annotator/dataset.py
ragas_annotator/exceptions.py
ragas_annotator/experiment.py
ragas_annotator/project.py
ragas_annotator/backends/__init__.py
ragas_annotator/backends/factory.py
ragas_annotator/backends/mock_notion.py
ragas_annotator/backends/notion_backend.py
ragas_annotator/embedding/__init__.py
ragas_annotator/embedding/base.py
ragas_annotator/llm/__init__.py
ragas_annotator/llm/llm.py
ragas_annotator/metric/__init__.py
ragas_annotator/metric/base.py
ragas_annotator/metric/decorator.py
ragas_annotator/metric/discrete.py
ragas_annotator/metric/numeric.py
ragas_annotator/metric/ranking.py
ragas_annotator/metric/result.py
ragas_annotator/model/__init__.py
ragas_annotator/model/notion_model.py
ragas_annotator/model/notion_typing.py
ragas_annotator/project/__init__.py
ragas_annotator/project/comparison.py
ragas_annotator/project/core.py
ragas_annotator/project/experiments.py
ragas_annotator/project/naming.py
ragas_annotator/prompt/__init__.py
ragas_annotator/prompt/base.py
ragas_annotator/prompt/dynamic_few_shot.py
ragas_annotator/tracing/__init__.py
ragas_annotator/tracing/langfuse.py
ragas_annotator-0.0.2.dist-info/LICENSE
ragas_annotator-0.0.2.dist-info/METADATA
ragas_annotator-0.0.2.dist-info/WHEEL
ragas_annotator-0.0.2.dist-info/entry_points.txt
ragas_annotator-0.0.2.dist-info/top_level.txt
ragas_annotator-0.0.2.dist-info/RECORD
